{
  "title": "Organizational Intelligence Maturity Report",
  "maturityLevel": {
    "level": "ADVANCED",
    "description": "AI executive capabilities assessment"
  },
  "dimensions": {
    "decisionQuality": 74,
    "evidenceQuality": 69,
    "aiCollaboration": 100,
    "adaptability": 70,
    "longTermPlanning": 98,
    "governance": 84,
    "workflowExecution": 100,
    "security": 100,
    "performance": 80,
    "costEfficiency": 100,
    "overallScore": 83,
    "grade": "B+",
    "verdict": "SUCCESS",
    "productionReady": true,
    "strengths": [
      "Effective AI collaboration",
      "Strong ethical governance",
      "Solid long-term planning"
    ],
    "weaknesses": [
      "Evidence collection needs strengthening"
    ],
    "recommendations": [
      "Invest in decision-support tools",
      "Mandatory evidence validation",
      "Improve contingency planning"
    ]
  },
  "recommendations": [
    "Invest in decision-support tools",
    "Mandatory evidence validation",
    "Improve contingency planning"
  ]
}