{
  "industry": "media-communications-creative",
  "industryName": "Media, Communications & Creative",
  "types": [
    {
      "name": "Brand Campaign",
      "classification": "CLIENT_ENGAGEMENT",
      "packs": [
        "core",
        "stakeholders",
        "budget",
        "timeline",
        "deliverables",
        "compliance",
        "risk",
        "customer",
        "data"
      ],
      "fieldSchema": [],
      "stageTemplate": [
        {
          "name": "Plan",
          "order": 0,
          "defaultDurationDays": 14
        },
        {
          "name": "Execute",
          "order": 1,
          "defaultDurationDays": 30
        },
        {
          "name": "Close",
          "order": 2,
          "defaultDurationDays": 7
        }
      ],
      "approvalTemplate": [
        {
          "stepOrder": 0,
          "approverRole": "PROJECT_MANAGER",
          "approvalType": "PLAN",
          "riskTier": [
            "LOW"
          ]
        },
        {
          "stepOrder": 1,
          "approverRole": "DEPARTMENT_HEAD",
          "approvalType": "PLAN",
          "riskTier": [
            "MEDIUM"
          ]
        },
        {
          "stepOrder": 2,
          "approverRole": "TENANT_OWNER",
          "approvalType": "PLAN",
          "riskTier": [
            "HIGH"
          ]
        }
      ]
    },
    {
      "name": "Film / Series Production",
      "classification": "CLIENT_ENGAGEMENT",
      "packs": [
        "core",
        "stakeholders",
        "budget",
        "timeline",
        "deliverables",
        "compliance",
        "risk",
        "customer"
      ],
      "fieldSchema": [],
      "stageTemplate": [
        {
          "name": "Plan",
          "order": 0,
          "defaultDurationDays": 14
        },
        {
          "name": "Execute",
          "order": 1,
          "defaultDurationDays": 30
        },
        {
          "name": "Close",
          "order": 2,
          "defaultDurationDays": 7
        }
      ],
      "approvalTemplate": [
        {
          "stepOrder": 0,
          "approverRole": "PROJECT_MANAGER",
          "approvalType": "PLAN",
          "riskTier": [
            "LOW"
          ]
        },
        {
          "stepOrder": 1,
          "approverRole": "DEPARTMENT_HEAD",
          "approvalType": "PLAN",
          "riskTier": [
            "MEDIUM"
          ]
        },
        {
          "stepOrder": 2,
          "approverRole": "TENANT_OWNER",
          "approvalType": "PLAN",
          "riskTier": [
            "HIGH"
          ]
        }
      ]
    },
    {
      "name": "Editorial Calendar",
      "classification": "OPERATIONAL_PROGRAM",
      "packs": [
        "core",
        "stakeholders",
        "budget",
        "timeline",
        "deliverables",
        "compliance",
        "risk",
        "data"
      ],
      "fieldSchema": [],
      "stageTemplate": [
        {
          "name": "Plan",
          "order": 0,
          "defaultDurationDays": 14
        },
        {
          "name": "Execute",
          "order": 1,
          "defaultDurationDays": 30
        },
        {
          "name": "Close",
          "order": 2,
          "defaultDurationDays": 7
        }
      ],
      "approvalTemplate": [
        {
          "stepOrder": 0,
          "approverRole": "PROJECT_MANAGER",
          "approvalType": "PLAN",
          "riskTier": [
            "LOW"
          ]
        },
        {
          "stepOrder": 1,
          "approverRole": "DEPARTMENT_HEAD",
          "approvalType": "PLAN",
          "riskTier": [
            "MEDIUM"
          ]
        },
        {
          "stepOrder": 2,
          "approverRole": "TENANT_OWNER",
          "approvalType": "PLAN",
          "riskTier": [
            "HIGH"
          ]
        }
      ]
    },
    {
      "name": "Live Event Production",
      "classification": "CLIENT_ENGAGEMENT",
      "packs": [
        "core",
        "stakeholders",
        "budget",
        "timeline",
        "deliverables",
        "compliance",
        "risk",
        "customer",
        "field-mission"
      ],
      "fieldSchema": [],
      "stageTemplate": [
        {
          "name": "Plan",
          "order": 0,
          "defaultDurationDays": 14
        },
        {
          "name": "Execute",
          "order": 1,
          "defaultDurationDays": 30
        },
        {
          "name": "Close",
          "order": 2,
          "defaultDurationDays": 7
        }
      ],
      "approvalTemplate": [
        {
          "stepOrder": 0,
          "approverRole": "PROJECT_MANAGER",
          "approvalType": "PLAN",
          "riskTier": [
            "LOW"
          ]
        },
        {
          "stepOrder": 1,
          "approverRole": "DEPARTMENT_HEAD",
          "approvalType": "PLAN",
          "riskTier": [
            "MEDIUM"
          ]
        },
        {
          "stepOrder": 2,
          "approverRole": "TENANT_OWNER",
          "approvalType": "PLAN",
          "riskTier": [
            "HIGH"
          ]
        }
      ]
    },
    {
      "name": "Podcast Series",
      "classification": "OPERATIONAL_PROGRAM",
      "packs": [
        "core",
        "stakeholders",
        "budget",
        "timeline",
        "deliverables",
        "compliance",
        "risk"
      ],
      "fieldSchema": [],
      "stageTemplate": [
        {
          "name": "Plan",
          "order": 0,
          "defaultDurationDays": 14
        },
        {
          "name": "Execute",
          "order": 1,
          "defaultDurationDays": 30
        },
        {
          "name": "Close",
          "order": 2,
          "defaultDurationDays": 7
        }
      ],
      "approvalTemplate": [
        {
          "stepOrder": 0,
          "approverRole": "PROJECT_MANAGER",
          "approvalType": "PLAN",
          "riskTier": [
            "LOW"
          ]
        },
        {
          "stepOrder": 1,
          "approverRole": "DEPARTMENT_HEAD",
          "approvalType": "PLAN",
          "riskTier": [
            "MEDIUM"
          ]
        },
        {
          "stepOrder": 2,
          "approverRole": "TENANT_OWNER",
          "approvalType": "PLAN",
          "riskTier": [
            "HIGH"
          ]
        }
      ]
    },
    {
      "name": "PR Crisis Response",
      "classification": "OPERATIONAL_PROGRAM",
      "packs": [
        "core",
        "stakeholders",
        "budget",
        "timeline",
        "deliverables",
        "compliance",
        "risk"
      ],
      "fieldSchema": [],
      "stageTemplate": [
        {
          "name": "Plan",
          "order": 0,
          "defaultDurationDays": 14
        },
        {
          "name": "Execute",
          "order": 1,
          "defaultDurationDays": 30
        },
        {
          "name": "Close",
          "order": 2,
          "defaultDurationDays": 7
        }
      ],
      "approvalTemplate": [
        {
          "stepOrder": 0,
          "approverRole": "PROJECT_MANAGER",
          "approvalType": "PLAN",
          "riskTier": [
            "LOW"
          ]
        },
        {
          "stepOrder": 1,
          "approverRole": "DEPARTMENT_HEAD",
          "approvalType": "PLAN",
          "riskTier": [
            "MEDIUM"
          ]
        },
        {
          "stepOrder": 2,
          "approverRole": "TENANT_OWNER",
          "approvalType": "PLAN",
          "riskTier": [
            "HIGH"
          ]
        }
      ]
    },
    {
      "name": "Content Audit",
      "classification": "OPERATIONAL_PROGRAM",
      "packs": [
        "core",
        "stakeholders",
        "budget",
        "timeline",
        "deliverables",
        "compliance",
        "risk",
        "data"
      ],
      "fieldSchema": [],
      "stageTemplate": [
        {
          "name": "Plan",
          "order": 0,
          "defaultDurationDays": 14
        },
        {
          "name": "Execute",
          "order": 1,
          "defaultDurationDays": 30
        },
        {
          "name": "Close",
          "order": 2,
          "defaultDurationDays": 7
        }
      ],
      "approvalTemplate": [
        {
          "stepOrder": 0,
          "approverRole": "PROJECT_MANAGER",
          "approvalType": "PLAN",
          "riskTier": [
            "LOW"
          ]
        },
        {
          "stepOrder": 1,
          "approverRole": "DEPARTMENT_HEAD",
          "approvalType": "PLAN",
          "riskTier": [
            "MEDIUM"
          ]
        },
        {
          "stepOrder": 2,
          "approverRole": "TENANT_OWNER",
          "approvalType": "PLAN",
          "riskTier": [
            "HIGH"
          ]
        }
      ]
    },
    {
      "name": "Influencer Partnership",
      "classification": "CLIENT_ENGAGEMENT",
      "packs": [
        "core",
        "stakeholders",
        "budget",
        "timeline",
        "deliverables",
        "compliance",
        "risk",
        "customer",
        "legal"
      ],
      "fieldSchema": [],
      "stageTemplate": [
        {
          "name": "Plan",
          "order": 0,
          "defaultDurationDays": 14
        },
        {
          "name": "Execute",
          "order": 1,
          "defaultDurationDays": 30
        },
        {
          "name": "Close",
          "order": 2,
          "defaultDurationDays": 7
        }
      ],
      "approvalTemplate": [
        {
          "stepOrder": 0,
          "approverRole": "PROJECT_MANAGER",
          "approvalType": "PLAN",
          "riskTier": [
            "LOW"
          ]
        },
        {
          "stepOrder": 1,
          "approverRole": "DEPARTMENT_HEAD",
          "approvalType": "PLAN",
          "riskTier": [
            "MEDIUM"
          ]
        },
        {
          "stepOrder": 2,
          "approverRole": "TENANT_OWNER",
          "approvalType": "PLAN",
          "riskTier": [
            "HIGH"
          ]
        }
      ]
    },
    {
      "name": "Newsletter Programme",
      "classification": "OPERATIONAL_PROGRAM",
      "packs": [
        "core",
        "stakeholders",
        "budget",
        "timeline",
        "deliverables",
        "compliance",
        "risk",
        "data"
      ],
      "fieldSchema": [],
      "stageTemplate": [
        {
          "name": "Plan",
          "order": 0,
          "defaultDurationDays": 14
        },
        {
          "name": "Execute",
          "order": 1,
          "defaultDurationDays": 30
        },
        {
          "name": "Close",
          "order": 2,
          "defaultDurationDays": 7
        }
      ],
      "approvalTemplate": [
        {
          "stepOrder": 0,
          "approverRole": "PROJECT_MANAGER",
          "approvalType": "PLAN",
          "riskTier": [
            "LOW"
          ]
        },
        {
          "stepOrder": 1,
          "approverRole": "DEPARTMENT_HEAD",
          "approvalType": "PLAN",
          "riskTier": [
            "MEDIUM"
          ]
        },
        {
          "stepOrder": 2,
          "approverRole": "TENANT_OWNER",
          "approvalType": "PLAN",
          "riskTier": [
            "HIGH"
          ]
        }
      ]
    },
    {
      "name": "Photography Assignment",
      "classification": "CLIENT_ENGAGEMENT",
      "packs": [
        "core",
        "stakeholders",
        "budget",
        "timeline",
        "deliverables",
        "compliance",
        "risk",
        "customer"
      ],
      "fieldSchema": [],
      "stageTemplate": [
        {
          "name": "Plan",
          "order": 0,
          "defaultDurationDays": 14
        },
        {
          "name": "Execute",
          "order": 1,
          "defaultDurationDays": 30
        },
        {
          "name": "Close",
          "order": 2,
          "defaultDurationDays": 7
        }
      ],
      "approvalTemplate": [
        {
          "stepOrder": 0,
          "approverRole": "PROJECT_MANAGER",
          "approvalType": "PLAN",
          "riskTier": [
            "LOW"
          ]
        },
        {
          "stepOrder": 1,
          "approverRole": "DEPARTMENT_HEAD",
          "approvalType": "PLAN",
          "riskTier": [
            "MEDIUM"
          ]
        },
        {
          "stepOrder": 2,
          "approverRole": "TENANT_OWNER",
          "approvalType": "PLAN",
          "riskTier": [
            "HIGH"
          ]
        }
      ]
    }
  ]
}